{
  "gpt_answer": {
    "No Poverty": {
      "score": 0.0,
      "reason": "No evidence found",
      "evidence": [],
      "evidence_type": "none"
    },
    "Zero Hunger": {
      "score": 0.0,
      "reason": "No evidence found",
      "evidence": [],
      "evidence_type": "none"
    },
    "Good Health and Well-being": {
      "score": 0.0,
      "reason": "No evidence found",
      "evidence": [],
      "evidence_type": "none"
    },
    "Quality Education": {
      "score": 8.0,
      "reason": "Focus on 'visual arts research' and 'aesthetic and social cultural literacy' aligns with Target 4.7.",
      "evidence": [
        "視覺藝術研究的專業基礎",
        "關懷社會文化的素養"
      ],
      "evidence_type": "explicit"
    },
    "Gender Equality": {
      "score": 0.0,
      "reason": "No evidence found",
      "evidence": [],
      "evidence_type": "none"
    },
    "Clean Water and Sanitation": {
      "score": 0.0,
      "reason": "No evidence found",
      "evidence": [],
      "evidence_type": "none"
    },
    "Affordable and Clean Energy": {
      "score": 0.0,
      "reason": "No evidence found",
      "evidence": [],
      "evidence_type": "none"
    },
    "Decent Work and Economic Growth": {
      "score": 0.0,
      "reason": "No evidence found",
      "evidence": [],
      "evidence_type": "none"
    },
    "Industry, Innovation and Infrastructure": {
      "score": 0.0,
      "reason": "No evidence found",
      "evidence": [],
      "evidence_type": "none"
    },
    "Reduced Inequalities": {
      "score": 0.0,
      "reason": "No evidence found",
      "evidence": [],
      "evidence_type": "none"
    },
    "Sustainable Cities and Communities": {
      "score": 0.0,
      "reason": "No evidence found",
      "evidence": [],
      "evidence_type": "none"
    },
    "Responsible Consumption and Production": {
      "score": 0.0,
      "reason": "No evidence found",
      "evidence": [],
      "evidence_type": "none"
    },
    "Climate Action": {
      "score": 0.0,
      "reason": "No evidence found",
      "evidence": [],
      "evidence_type": "none"
    },
    "Life Below Water": {
      "score": 0.0,
      "reason": "No evidence found",
      "evidence": [],
      "evidence_type": "none"
    },
    "Life on Land": {
      "score": 0.0,
      "reason": "No evidence found",
      "evidence": [],
      "evidence_type": "none"
    },
    "Peace, Justice and Strong Institutions": {
      "score": 0.0,
      "reason": "No evidence found",
      "evidence": [],
      "evidence_type": "none"
    },
    "Partnerships for the Goals": {
      "score": 0.0,
      "reason": "No evidence found",
      "evidence": [],
      "evidence_type": "none"
    }
  },
  "gemini_answer": [
    {
      "No Poverty": {
        "score": 0.0,
        "reason": "No evidence found",
        "evidence": [],
        "evidence_type": "none"
      },
      "Zero Hunger": {
        "score": 0.0,
        "reason": "No evidence found",
        "evidence": [],
        "evidence_type": "none"
      },
      "Good Health and Well-being": {
        "score": 0.0,
        "reason": "No evidence found",
        "evidence": [],
        "evidence_type": "none"
      },
      "Quality Education": {
        "score": 7.5,
        "reason": "The course is a form of tertiary education (Target 4.3) and aims to cultivate appreciation for culture's contribution to development (Target 4.7).",
        "evidence": [
          "建立以人文社會科學進行視覺藝術研究的專業基礎",
          "培養美學及關懷社會文化的素養",
          "Modern Visual Arts and Society"
        ],
        "evidence_type": "explicit"
      },
      "Gender Equality": {
        "score": 0.0,
        "reason": "No evidence found",
        "evidence": [],
        "evidence_type": "none"
      },
      "Clean Water and Sanitation": {
        "score": 0.0,
        "reason": "No evidence found",
        "evidence": [],
        "evidence_type": "none"
      },
      "Affordable and Clean Energy": {
        "score": 0.0,
        "reason": "No evidence found",
        "evidence": [],
        "evidence_type": "none"
      },
      "Decent Work and Economic Growth": {
        "score": 1.0,
        "reason": "The course discusses the context of 'industrialization and urbanization' and the role of the artist, which tangentially relates to creativity and innovation (Target 8.3).",
        "evidence": [
          "隨著工業化和都市化的累積發展",
          "藝術家作為獨立藝術家的主體性"
        ],
        "evidence_type": "inferred"
      },
      "Industry, Innovation and Infrastructure": {
        "score": 4.5,
        "reason": "The course analyzes art's response to 'industrialization' (Target 9.2) and focuses on artistic 'innovation' and 'experimentation' (革新實驗), linking to Target 9.5.",
        "evidence": [
          "隨著工業化和都市化的累積發展",
          "自我反思與革新實驗",
          "實驗性格"
        ],
        "evidence_type": "explicit"
      },
      "Reduced Inequalities": {
        "score": 2.5,
        "reason": "The course's sociological approach to art as a 'form of rebellion and revolution' can be inferred as a critique of social structures, relating to inequality (Target 10.3).",
        "evidence": [
          "藝術成為一種反叛與革命的形式",
          "突顯出藝術與社會的互動關連"
        ],
        "evidence_type": "inferred"
      },
      "Sustainable Cities and Communities": {
        "score": 6.0,
        "reason": "The course directly links modern art to 'urbanization' (Target 11.3) and is fundamentally about studying and safeguarding cultural heritage, specifically modern painting (Target 11.4).",
        "evidence": [
          "隨著工業化和都市化的累積發展",
          "現代視覺藝術與社會",
          "Modern Visual Arts and Society"
        ],
        "evidence_type": "explicit"
      },
      "Responsible Consumption and Production": {
        "score": 0.0,
        "reason": "No evidence found",
        "evidence": [],
        "evidence_type": "none"
      },
      "Climate Action": {
        "score": 0.0,
        "reason": "No evidence found",
        "evidence": [],
        "evidence_type": "none"
      },
      "Life Below Water": {
        "score": 0.0,
        "reason": "No evidence found",
        "evidence": [],
        "evidence_type": "none"
      },
      "Life on Land": {
        "score": 0.0,
        "reason": "No evidence found",
        "evidence": [],
        "evidence_type": "none"
      },
      "Peace, Justice and Strong Institutions": {
        "score": 1.5,
        "reason": "The course discusses art as a 'form of rebellion and revolution' and mentions 'political practice,' which can be inferred as a critique of societal institutions (Target 16.6).",
        "evidence": [
          "藝術成為一種反叛與革命的形式",
          "政治實踐的不同強調"
        ],
        "evidence_type": "inferred"
      },
      "Partnerships for the Goals": {
        "score": 0.0,
        "reason": "No evidence found",
        "evidence": [],
        "evidence_type": "none"
      }
    }
  ],
  "gpt_critique": {
    "critique": "Model B's analysis provides a more nuanced understanding of the course's implications for several SDGs, particularly in education and social issues.",
    "revisions": {
      "Quality Education": {
        "your_original": 8.0,
        "model_b_score": 7.5,
        "your_revised": 7.5,
        "reason": "Model B's score reflects a more accurate alignment with the course's focus on tertiary education."
      },
      "Decent Work and Economic Growth": {
        "your_original": 0.0,
        "model_b_score": 1.0,
        "your_revised": 1.0,
        "reason": "Model B identifies relevant connections to industrialization and creativity."
      },
      "Industry, Innovation and Infrastructure": {
        "your_original": 0.0,
        "model_b_score": 4.5,
        "your_revised": 4.5,
        "reason": "Model B's score captures the course's emphasis on art's response to industrialization."
      },
      "Reduced Inequalities": {
        "your_original": 0.0,
        "model_b_score": 2.5,
        "your_revised": 2.5,
        "reason": "Model B's interpretation of art as a critique of social structures is valid."
      },
      "Sustainable Cities and Communities": {
        "your_original": 0.0,
        "model_b_score": 6.0,
        "your_revised": 6.0,
        "reason": "Model B accurately links modern art to urbanization and cultural heritage."
      },
      "Peace, Justice and Strong Institutions": {
        "your_original": 0.0,
        "model_b_score": 1.5,
        "your_revised": 1.5,
        "reason": "Model B's score reflects the course's discussion on art as a form of rebellion."
      }
    }
  },
  "gemini_critique": {
    "critique": "Model A provided valuable insights regarding cultural heritage and tertiary education, leading to revisions in my scores for SDG 4 and SDG 11. For other SDGs, Model A's inferences were too indirect.",
    "revisions": {
      "SDG_4 (Quality Education)": {
        "your_original": 8.0,
        "model_b_score": 8.0,
        "your_revised": 8.0,
        "reason": "Model A's reasoning for SDG 4.3 (tertiary education) is valid and complements my focus on 4.7, making the overall assessment more complete."
      },
      "SDG_11 (Sustainable Cities and Communities)": {
        "your_original": 0.0,
        "model_b_score": 0.0,
        "your_revised": 6.0,
        "reason": "Model A accurately identifies the course's contribution to safeguarding cultural heritage (Target 11.4), which I overlooked."
      }
    }
  },
  "gpt_judge_final": {},
  "gemini_judge_final": {
    "No Poverty": {
      "final_score": 0.0,
      "source": "model_a",
      "reasoning": "The course content focuses on art history, theory, and sociology, with no explicit or implicit mention of poverty eradication or related economic targets.",
      "model_comparison": {
        "model_a_original": 0.0,
        "model_a_revised": null,
        "model_b_original": 0.0,
        "model_b_revised": null
      }
    },
    "Zero Hunger": {
      "final_score": 0.0,
      "source": "model_a",
      "reasoning": "The course content is entirely unrelated to food security, nutrition, sustainable agriculture, or food systems.",
      "model_comparison": {
        "model_a_original": 0.0,
        "model_a_revised": null,
        "model_b_original": 0.0,
        "model_b_revised": null
      }
    },
    "Good Health and Well-being": {
      "final_score": 0.0,
      "source": "model_a",
      "reasoning": "The course does not address health, well-being, disease prevention, or healthcare services in any capacity.",
      "model_comparison": {
        "model_a_original": 0.0,
        "model_a_revised": null,
        "model_b_original": 0.0,
        "model_b_revised": null
      }
    },
    "Quality Education": {
      "final_score": 8.0,
      "source": "synthesized",
      "reasoning": "The course is a university-level elective (Target 4.3) and explicitly aims to cultivate aesthetic and social-cultural literacy, including an appreciation for culture's contribution to society (Target 4.7).",
      "model_comparison": {
        "model_a_original": 8.0,
        "model_a_revised": 7.5,
        "model_b_original": 7.5,
        "model_b_revised": 8.0
      }
    },
    "Gender Equality": {
      "final_score": 0.0,
      "source": "model_a",
      "reasoning": "The course syllabus does not contain any explicit or implicit references to gender equality, women's empowerment, or related issues.",
      "model_comparison": {
        "model_a_original": 0.0,
        "model_a_revised": null,
        "model_b_original": 0.0,
        "model_b_revised": null
      }
    },
    "Clean Water and Sanitation": {
      "final_score": 0.0,
      "source": "model_a",
      "reasoning": "The course content is entirely unrelated to water resources, sanitation, hygiene, or water pollution.",
      "model_comparison": {
        "model_a_original": 0.0,
        "model_a_revised": null,
        "model_b_original": 0.0,
        "model_b_revised": null
      }
    },
    "Affordable and Clean Energy": {
      "final_score": 0.0,
      "source": "model_a",
      "reasoning": "The course does not discuss energy, renewable sources, energy efficiency, or related infrastructure.",
      "model_comparison": {
        "model_a_original": 0.0,
        "model_a_revised": null,
        "model_b_original": 0.0,
        "model_b_revised": null
      }
    },
    "Decent Work and Economic Growth": {
      "final_score": 0.5,
      "source": "synthesized",
      "reasoning": "While the course discusses art's response to industrialization and artistic creativity, the link to specific targets like decent job creation or economic growth (Target 8.3) is very indirect and not a primary focus.",
      "model_comparison": {
        "model_a_original": 0.0,
        "model_a_revised": 1.0,
        "model_b_original": 1.0,
        "model_b_revised": null
      }
    },
    "Industry, Innovation and Infrastructure": {
      "final_score": 4.5,
      "source": "model_b",
      "reasoning": "The course extensively discusses modern art's '革新實驗' (innovation and experimentation) and '實驗性格' (experimental character), aligning with the spirit of innovation in Target 9.5.",
      "model_comparison": {
        "model_a_original": 0.0,
        "model_a_revised": 4.5,
        "model_b_original": 4.5,
        "model_b_revised": null
      }
    },
    "Reduced Inequalities": {
      "final_score": 2.5,
      "source": "model_b",
      "reasoning": "The course examines art as a '反叛與革命的形式' (form of rebellion and revolution) and its interaction with society, which can be inferred as a critique of social structures that may perpetuate inequalities (Target 10.3).",
      "model_comparison": {
        "model_a_original": 0.0,
        "model_a_revised": 2.5,
        "model_b_original": 2.5,
        "model_b_revised": null
      }
    },
    "Sustainable Cities and Communities": {
      "final_score": 6.0,
      "source": "model_b",
      "reasoning": "The course directly examines the impact of '都市化' (urbanization) on modern art (Target 11.3) and is fundamentally dedicated to the study and appreciation of '視覺藝術' (visual arts), thereby contributing to safeguarding cultural heritage (Target 11.4).",
      "model_comparison": {
        "model_a_original": 0.0,
        "model_a_revised": 6.0,
        "model_b_original": 6.0,
        "model_b_revised": 6.0
      }
    },
    "Responsible Consumption and Production": {
      "final_score": 0.0,
      "source": "model_a",
      "reasoning": "The course content does not address consumption patterns, production methods, waste management, or resource efficiency.",
      "model_comparison": {
        "model_a_original": 0.0,
        "model_a_revised": null,
        "model_b_original": 0.0,
        "model_b_revised": null
      }
    },
    "Climate Action": {
      "final_score": 0.0,
      "source": "model_a",
      "reasoning": "The course content does not discuss climate change, environmental hazards, or related policies.",
      "model_comparison": {
        "model_a_original": 0.0,
        "model_a_revised": null,
        "model_b_original": 0.0,
        "model_b_revised": null
      }
    },
    "Life Below Water": {
      "final_score": 0.0,
      "source": "model_a",
      "reasoning": "The course content is entirely unrelated to marine ecosystems, ocean health, or sustainable fisheries.",
      "model_comparison": {
        "model_a_original": 0.0,
        "model_a_revised": null,
        "model_b_original": 0.0,
        "model_b_revised": null
      }
    },
    "Life on Land": {
      "final_score": 0.0,
      "source": "model_a",
      "reasoning": "The course content is entirely unrelated to terrestrial ecosystems, biodiversity, deforestation, or land degradation.",
      "model_comparison": {
        "model_a_original": 0.0,
        "model_a_revised": null,
        "model_b_original": 0.0,
        "model_b_revised": null
      }
    },
    "Peace, Justice and Strong Institutions": {
      "final_score": 1.5,
      "source": "model_b",
      "reasoning": "The course explores art as a '反叛與革命的形式' (form of rebellion and revolution) and its '政治實踐' (political practice), which can be inferred as a critique of societal structures and institutions (Target 16.6).",
      "model_comparison": {
        "model_a_original": 0.0,
        "model_a_revised": 1.5,
        "model_b_original": 1.5,
        "model_b_revised": null
      }
    },
    "Partnerships for the Goals": {
      "final_score": 0.0,
      "source": "model_a",
      "reasoning": "The course content does not discuss global partnerships, resource mobilization, or multi-stakeholder cooperation for sustainable development.",
      "model_comparison": {
        "model_a_original": 0.0,
        "model_a_revised": null,
        "model_b_original": 0.0,
        "model_b_revised": null
      }
    }
  }
}