{
  "gpt_answer": {
    "No Poverty": {
      "score": 0.0,
      "reason": "No evidence found",
      "evidence": [],
      "evidence_type": "none"
    },
    "Zero Hunger": {
      "score": 0.0,
      "reason": "No evidence found",
      "evidence": [],
      "evidence_type": "none"
    },
    "Good Health and Well-being": {
      "score": 0.0,
      "reason": "No evidence found",
      "evidence": [],
      "evidence_type": "none"
    },
    "Quality Education": {
      "score": 3.0,
      "reason": "Course contributes to education through probability concepts applicable in various fields.",
      "evidence": [
        "properly define the basic concepts of probability space",
        "understand the definitions and properties of conditional probability"
      ],
      "evidence_type": "inferred"
    },
    "Gender Equality": {
      "score": 0.0,
      "reason": "No evidence found",
      "evidence": [],
      "evidence_type": "none"
    },
    "Clean Water and Sanitation": {
      "score": 0.0,
      "reason": "No evidence found",
      "evidence": [],
      "evidence_type": "none"
    },
    "Affordable and Clean Energy": {
      "score": 0.0,
      "reason": "No evidence found",
      "evidence": [],
      "evidence_type": "none"
    },
    "Decent Work and Economic Growth": {
      "score": 0.0,
      "reason": "No evidence found",
      "evidence": [],
      "evidence_type": "none"
    },
    "Industry, Innovation and Infrastructure": {
      "score": 0.0,
      "reason": "No evidence found",
      "evidence": [],
      "evidence_type": "none"
    },
    "Reduced Inequalities": {
      "score": 0.0,
      "reason": "No evidence found",
      "evidence": [],
      "evidence_type": "none"
    },
    "Sustainable Cities and Communities": {
      "score": 0.0,
      "reason": "No evidence found",
      "evidence": [],
      "evidence_type": "none"
    },
    "Responsible Consumption and Production": {
      "score": 0.0,
      "reason": "No evidence found",
      "evidence": [],
      "evidence_type": "none"
    },
    "Climate Action": {
      "score": 0.0,
      "reason": "No evidence found",
      "evidence": [],
      "evidence_type": "none"
    },
    "Life Below Water": {
      "score": 0.0,
      "reason": "No evidence found",
      "evidence": [],
      "evidence_type": "none"
    },
    "Life on Land": {
      "score": 0.0,
      "reason": "No evidence found",
      "evidence": [],
      "evidence_type": "none"
    },
    "Peace, Justice and Strong Institutions": {
      "score": 0.0,
      "reason": "No evidence found",
      "evidence": [],
      "evidence_type": "none"
    },
    "Partnerships for the Goals": {
      "score": 0.0,
      "reason": "No evidence found",
      "evidence": [],
      "evidence_type": "none"
    }
  },
  "gemini_answer": [
    {
      "No Poverty": {
        "score": 0.0,
        "reason": "No evidence found",
        "evidence": [],
        "evidence_type": "none"
      },
      "Zero Hunger": {
        "score": 0.0,
        "reason": "No evidence found",
        "evidence": [],
        "evidence_type": "none"
      },
      "Good Health and Well-being": {
        "score": 0.0,
        "reason": "No evidence found",
        "evidence": [],
        "evidence_type": "none"
      },
      "Quality Education": {
        "score": 8.0,
        "reason": "As a university course, it directly provides quality tertiary education (Target 4.3) and develops skills relevant for employment and further scientific study (Target 4.4).",
        "evidence": [
          "Type of Credit: Required",
          "Course Department:Mathematical Sciences/B/2",
          "A course on mathematical probability"
        ],
        "evidence_type": "explicit"
      },
      "Gender Equality": {
        "score": 0.0,
        "reason": "No evidence found",
        "evidence": [],
        "evidence_type": "none"
      },
      "Clean Water and Sanitation": {
        "score": 0.0,
        "reason": "No evidence found",
        "evidence": [],
        "evidence_type": "none"
      },
      "Affordable and Clean Energy": {
        "score": 0.0,
        "reason": "No evidence found",
        "evidence": [],
        "evidence_type": "none"
      },
      "Decent Work and Economic Growth": {
        "score": 4.5,
        "reason": "The course provides foundational skills in probability, a tool for innovation and technological upgrading in high-value sectors, contributing to economic productivity (Target 8.2).",
        "evidence": [
          "Probability",
          "relating these to real-world applications"
        ],
        "evidence_type": "inferred"
      },
      "Industry, Innovation and Infrastructure": {
        "score": 7.5,
        "reason": "The course teaches fundamental probability theory, a cornerstone for enhancing scientific research, technological capabilities, and innovation across various industrial sectors (Target 9.5).",
        "evidence": [
          "mathematical probability",
          "limit theorems",
          "real-world applications"
        ],
        "evidence_type": "inferred"
      },
      "Reduced Inequalities": {
        "score": 0.0,
        "reason": "No evidence found",
        "evidence": [],
        "evidence_type": "none"
      },
      "Sustainable Cities and Communities": {
        "score": 0.0,
        "reason": "No evidence found",
        "evidence": [],
        "evidence_type": "none"
      },
      "Responsible Consumption and Production": {
        "score": 0.0,
        "reason": "No evidence found",
        "evidence": [],
        "evidence_type": "none"
      },
      "Climate Action": {
        "score": 0.0,
        "reason": "No evidence found",
        "evidence": [],
        "evidence_type": "none"
      },
      "Life Below Water": {
        "score": 0.0,
        "reason": "No evidence found",
        "evidence": [],
        "evidence_type": "none"
      },
      "Life on Land": {
        "score": 0.0,
        "reason": "No evidence found",
        "evidence": [],
        "evidence_type": "none"
      },
      "Peace, Justice and Strong Institutions": {
        "score": 0.0,
        "reason": "No evidence found",
        "evidence": [],
        "evidence_type": "none"
      },
      "Partnerships for the Goals": {
        "score": 6.0,
        "reason": "Builds foundational knowledge for statistics, essential for statistical capacity-building and developing measurements of progress for sustainable development (Targets 17.18, 17.19).",
        "evidence": [
          "mathematical probability",
          "axioms of probability",
          "limit theorems"
        ],
        "evidence_type": "inferred"
      }
    }
  ],
  "gpt_critique": {
    "critique": "Model B's analysis provides a more comprehensive understanding of the course's contributions to education and economic growth.",
    "revisions": {
      "Quality Education": {
        "your_original": 3.0,
        "model_b_score": 8.0,
        "your_revised": 8.0,
        "reason": "Model B highlights the course's direct contribution to quality tertiary education and skill development."
      },
      "Decent Work and Economic Growth": {
        "your_original": 0.0,
        "model_b_score": 4.5,
        "your_revised": 4.5,
        "reason": "Model B identifies the course's role in foundational skills for economic productivity."
      },
      "Industry, Innovation and Infrastructure": {
        "your_original": 0.0,
        "model_b_score": 7.5,
        "your_revised": 7.5,
        "reason": "Model B emphasizes the course's importance in enhancing scientific research and innovation."
      },
      "Partnerships for the Goals": {
        "your_original": 0.0,
        "model_b_score": 6.0,
        "your_revised": 6.0,
        "reason": "Model B connects the course to statistical capacity-building for sustainable development."
      }
    }
  },
  "gemini_critique": {
    "critique": "Model A provides a more comprehensive and accurate assessment, particularly in recognizing the explicit and inferred contributions of a university-level probability course to several SDGs beyond just education.",
    "revisions": {
      "Quality Education": {
        "your_original": 3.0,
        "model_b_score": 3.0,
        "your_revised": 8.0,
        "reason": "As a required university course, it directly provides tertiary education (Target 4.3) and develops skills for further study, aligning with Model A's explicit reasoning."
      },
      "Decent Work and Economic Growth": {
        "your_original": 0.0,
        "model_b_score": 0.0,
        "your_revised": 4.5,
        "reason": "Probability skills are foundational for innovation and technological upgrading, contributing to economic productivity (Target 8.2) as inferred by Model A."
      },
      "Industry, Innovation and Infrastructure": {
        "your_original": 0.0,
        "model_b_score": 0.0,
        "your_revised": 7.5,
        "reason": "Probability theory is a cornerstone for scientific research and technological innovation (Target 9.5), a strong inference made by Model A."
      },
      "Partnerships for the Goals": {
        "your_original": 0.0,
        "model_b_score": 0.0,
        "your_revised": 6.0,
        "reason": "Foundational probability knowledge is essential for statistical capacity-building and measuring sustainable development progress (Targets 17.18, 17.19), as Model A inferred."
      }
    }
  },
  "gpt_judge_final": {
    "No Poverty": {
      "final_score": 0.0,
      "source": "synthesized",
      "reasoning": "Both models found no evidence related to poverty, justifying a score of zero.",
      "model_comparison": {
        "model_a_original": 0.0,
        "model_a_revised": 0.0,
        "model_b_original": 0.0,
        "model_b_revised": 0.0
      }
    },
    "Zero Hunger": {
      "final_score": 0.0,
      "source": "synthesized",
      "reasoning": "No evidence was found in either model regarding hunger, leading to a score of zero.",
      "model_comparison": {
        "model_a_original": 0.0,
        "model_a_revised": 0.0,
        "model_b_original": 0.0,
        "model_b_revised": 0.0
      }
    },
    "Good Health and Well-being": {
      "final_score": 0.0,
      "source": "synthesized",
      "reasoning": "Both models reported no evidence related to health, confirming a score of zero.",
      "model_comparison": {
        "model_a_original": 0.0,
        "model_a_revised": 0.0,
        "model_b_original": 0.0,
        "model_b_revised": 0.0
      }
    },
    "Quality Education": {
      "final_score": 8.0,
      "source": "synthesized",
      "reasoning": "Both models revised their scores to reflect the course's strong contribution to quality education, aligning with SDG targets.",
      "model_comparison": {
        "model_a_original": 3.0,
        "model_a_revised": 8.0,
        "model_b_original": 8.0,
        "model_b_revised": 8.0
      }
    },
    "Gender Equality": {
      "final_score": 0.0,
      "source": "synthesized",
      "reasoning": "No evidence was found in either model regarding gender equality, justifying a score of zero.",
      "model_comparison": {
        "model_a_original": 0.0,
        "model_a_revised": 0.0,
        "model_b_original": 0.0,
        "model_b_revised": 0.0
      }
    },
    "Clean Water and Sanitation": {
      "final_score": 0.0,
      "source": "synthesized",
      "reasoning": "Both models found no evidence related to clean water and sanitation, confirming a score of zero.",
      "model_comparison": {
        "model_a_original": 0.0,
        "model_a_revised": 0.0,
        "model_b_original": 0.0,
        "model_b_revised": 0.0
      }
    },
    "Affordable and Clean Energy": {
      "final_score": 0.0,
      "source": "synthesized",
      "reasoning": "No evidence was found in either model regarding energy, leading to a score of zero.",
      "model_comparison": {
        "model_a_original": 0.0,
        "model_a_revised": 0.0,
        "model_b_original": 0.0,
        "model_b_revised": 0.0
      }
    },
    "Decent Work and Economic Growth": {
      "final_score": 4.5,
      "source": "synthesized",
      "reasoning": "Both models recognized the course's contribution to economic productivity through foundational skills in probability.",
      "model_comparison": {
        "model_a_original": 0.0,
        "model_a_revised": 4.5,
        "model_b_original": 4.5,
        "model_b_revised": 4.5
      }
    },
    "Industry, Innovation and Infrastructure": {
      "final_score": 7.5,
      "source": "synthesized",
      "reasoning": "Both models acknowledged the course's role in enhancing scientific research and innovation, justifying a high score.",
      "model_comparison": {
        "model_a_original": 0.0,
        "model_a_revised": 7.5,
        "model_b_original": 7.5,
        "model_b_revised": 7.5
      }
    },
    "Reduced Inequalities": {
      "final_score": 0.0,
      "source": "synthesized",
      "reasoning": "No evidence was found in either model regarding reduced inequalities, confirming a score of zero.",
      "model_comparison": {
        "model_a_original": 0.0,
        "model_a_revised": 0.0,
        "model_b_original": 0.0,
        "model_b_revised": 0.0
      }
    },
    "Sustainable Cities and Communities": {
      "final_score": 0.0,
      "source": "synthesized",
      "reasoning": "Both models found no evidence related to sustainable cities, justifying a score of zero.",
      "model_comparison": {
        "model_a_original": 0.0,
        "model_a_revised": 0.0,
        "model_b_original": 0.0,
        "model_b_revised": 0.0
      }
    },
    "Responsible Consumption and Production": {
      "final_score": 0.0,
      "source": "synthesized",
      "reasoning": "No evidence was found in either model regarding responsible consumption, leading to a score of zero.",
      "model_comparison": {
        "model_a_original": 0.0,
        "model_a_revised": 0.0,
        "model_b_original": 0.0,
        "model_b_revised": 0.0
      }
    },
    "Climate Action": {
      "final_score": 0.0,
      "source": "synthesized",
      "reasoning": "Both models reported no evidence related to climate action, confirming a score of zero.",
      "model_comparison": {
        "model_a_original": 0.0,
        "model_a_revised": 0.0,
        "model_b_original": 0.0,
        "model_b_revised": 0.0
      }
    },
    "Life Below Water": {
      "final_score": 0.0,
      "source": "synthesized",
      "reasoning": "No evidence was found in either model regarding life below water, leading to a score of zero.",
      "model_comparison": {
        "model_a_original": 0.0,
        "model_a_revised": 0.0,
        "model_b_original": 0.0,
        "model_b_revised": 0.0
      }
    },
    "Life on Land": {
      "final_score": 0.0,
      "source": "synthesized",
      "reasoning": "Both models found no evidence related to life on land, confirming a score of zero.",
      "model_comparison": {
        "model_a_original": 0.0,
        "model_a_revised": 0.0,
        "model_b_original": 0.0,
        "model_b_revised": 0.0
      }
    },
    "Peace, Justice and Strong Institutions": {
      "final_score": 0.0,
      "source": "synthesized",
      "reasoning": "No evidence was found in either model regarding peace and justice, leading to a score of zero.",
      "model_comparison": {
        "model_a_original": 0.0,
        "model_a_revised": 0.0,
        "model_b_original": 0.0,
        "model_b_revised": 0.0
      }
    },
    "Partnerships for the Goals": {
      "final_score": 6.0,
      "source": "synthesized",
      "reasoning": "Both models recognized the course's contribution to statistical capacity-building, justifying a significant score.",
      "model_comparison": {
        "model_a_original": 0.0,
        "model_a_revised": 6.0,
        "model_b_original": 6.0,
        "model_b_revised": 6.0
      }
    }
  },
  "gemini_judge_final": {
    "No Poverty": {
      "final_score": 0.0,
      "source": "model_a",
      "reasoning": "The course content is purely mathematical probability theory and does not directly or indirectly address poverty eradication or related economic resources.",
      "model_comparison": {
        "model_a_original": 0.0,
        "model_a_revised": null,
        "model_b_original": 0.0,
        "model_b_revised": null
      }
    },
    "Zero Hunger": {
      "final_score": 0.0,
      "source": "model_a",
      "reasoning": "The course focuses on mathematical probability and has no connection to food security, nutrition, sustainable agriculture, or related targets.",
      "model_comparison": {
        "model_a_original": 0.0,
        "model_a_revised": null,
        "model_b_original": 0.0,
        "model_b_revised": null
      }
    },
    "Good Health and Well-being": {
      "final_score": 0.0,
      "source": "model_a",
      "reasoning": "The course content is mathematical probability theory and does not explicitly or implicitly relate to health outcomes, disease prevention, or well-being.",
      "model_comparison": {
        "model_a_original": 0.0,
        "model_a_revised": null,
        "model_b_original": 0.0,
        "model_b_revised": null
      }
    },
    "Quality Education": {
      "final_score": 8.0,
      "source": "model_b",
      "reasoning": "As a required university course in Mathematical Sciences, it directly provides quality tertiary education (Target 4.3) and develops advanced analytical skills (Target 4.4).",
      "model_comparison": {
        "model_a_original": 3.0,
        "model_a_revised": 8.0,
        "model_b_original": 8.0,
        "model_b_revised": null
      }
    },
    "Gender Equality": {
      "final_score": 0.0,
      "source": "model_a",
      "reasoning": "The course content is purely mathematical and does not address gender equality, discrimination, violence, or women's empowerment.",
      "model_comparison": {
        "model_a_original": 0.0,
        "model_a_revised": null,
        "model_b_original": 0.0,
        "model_b_revised": null
      }
    },
    "Clean Water and Sanitation": {
      "final_score": 0.0,
      "source": "model_a",
      "reasoning": "The course focuses on mathematical probability and has no connection to water quality, sanitation, water-use efficiency, or water-related ecosystems.",
      "model_comparison": {
        "model_a_original": 0.0,
        "model_a_revised": null,
        "model_b_original": 0.0,
        "model_b_revised": null
      }
    },
    "Affordable and Clean Energy": {
      "final_score": 0.0,
      "source": "model_a",
      "reasoning": "The course content is mathematical probability theory and does not relate to energy access, renewable energy, or energy efficiency.",
      "model_comparison": {
        "model_a_original": 0.0,
        "model_a_revised": null,
        "model_b_original": 0.0,
        "model_b_revised": null
      }
    },
    "Decent Work and Economic Growth": {
      "final_score": 4.5,
      "source": "model_b",
      "reasoning": "The course provides foundational probability skills, crucial for data analysis, risk assessment, and modeling, contributing to technological upgrading and economic productivity (Target 8.2).",
      "model_comparison": {
        "model_a_original": 0.0,
        "model_a_revised": 4.5,
        "model_b_original": 4.5,
        "model_b_revised": null
      }
    },
    "Industry, Innovation and Infrastructure": {
      "final_score": 7.5,
      "source": "model_b",
      "reasoning": "Probability theory is a fundamental mathematical tool essential for scientific research, technological development, and innovation across various industrial sectors, directly supporting Target 9.5.",
      "model_comparison": {
        "model_a_original": 0.0,
        "model_a_revised": 7.5,
        "model_b_original": 7.5,
        "model_b_revised": null
      }
    },
    "Reduced Inequalities": {
      "final_score": 0.0,
      "source": "model_a",
      "reasoning": "The course content is purely mathematical and does not address income inequality, social inclusion, or discriminatory practices.",
      "model_comparison": {
        "model_a_original": 0.0,
        "model_a_revised": null,
        "model_b_original": 0.0,
        "model_b_revised": null
      }
    },
    "Sustainable Cities and Communities": {
      "final_score": 0.0,
      "source": "model_a",
      "reasoning": "The course focuses on mathematical probability and has no connection to urban planning, infrastructure, heritage protection, or disaster resilience in communities.",
      "model_comparison": {
        "model_a_original": 0.0,
        "model_a_revised": null,
        "model_b_original": 0.0,
        "model_b_revised": null
      }
    },
    "Responsible Consumption and Production": {
      "final_score": 0.0,
      "source": "model_a",
      "reasoning": "The course content is mathematical probability theory and does not relate to resource management, waste reduction, or sustainable business practices.",
      "model_comparison": {
        "model_a_original": 0.0,
        "model_a_revised": null,
        "model_b_original": 0.0,
        "model_b_revised": null
      }
    },
    "Climate Action": {
      "final_score": 0.0,
      "source": "model_a",
      "reasoning": "The course focuses on mathematical probability and does not explicitly or implicitly address climate change mitigation, adaptation, or awareness.",
      "model_comparison": {
        "model_a_original": 0.0,
        "model_a_revised": null,
        "model_b_original": 0.0,
        "model_b_revised": null
      }
    },
    "Life Below Water": {
      "final_score": 0.0,
      "source": "model_a",
      "reasoning": "The course content is mathematical probability theory and has no connection to marine ecosystems, ocean health, or sustainable fisheries.",
      "model_comparison": {
        "model_a_original": 0.0,
        "model_a_revised": null,
        "model_b_original": 0.0,
        "model_b_revised": null
      }
    },
    "Life on Land": {
      "final_score": 0.0,
      "source": "model_a",
      "reasoning": "The course focuses on mathematical probability and has no connection to terrestrial ecosystems, biodiversity, or sustainable land management.",
      "model_comparison": {
        "model_a_original": 0.0,
        "model_a_revised": null,
        "model_b_original": 0.0,
        "model_b_revised": null
      }
    },
    "Peace, Justice and Strong Institutions": {
      "final_score": 0.0,
      "source": "model_a",
      "reasoning": "The course content is purely mathematical and does not address violence, justice, rule of law, or institutional development.",
      "model_comparison": {
        "model_a_original": 0.0,
        "model_a_revised": null,
        "model_b_original": 0.0,
        "model_b_revised": null
      }
    },
    "Partnerships for the Goals": {
      "final_score": 6.0,
      "source": "model_b",
      "reasoning": "The course provides foundational knowledge in probability, essential for statistical capacity-building (Target 17.18) and developing measurements of progress for sustainable development (Target 17.19).",
      "model_comparison": {
        "model_a_original": 0.0,
        "model_a_revised": 6.0,
        "model_b_original": 6.0,
        "model_b_revised": null
      }
    }
  }
}