{
  "gpt_answer": {
    "No Poverty": {
      "score": 0.0,
      "reason": "No evidence found",
      "evidence": [],
      "evidence_type": "none"
    },
    "Zero Hunger": {
      "score": 0.0,
      "reason": "No evidence found",
      "evidence": [],
      "evidence_type": "none"
    },
    "Good Health and Well-being": {
      "score": 0.0,
      "reason": "No evidence found",
      "evidence": [],
      "evidence_type": "none"
    },
    "Quality Education": {
      "score": 8.0,
      "reason": "Course enhances skills and knowledge, linking to Target 4.4 ('relevant skills for employment').",
      "evidence": [
        "Students will acquire and apply expertise",
        "Students will acquire problem solving skills"
      ],
      "evidence_type": "explicit"
    },
    "Gender Equality": {
      "score": 0.0,
      "reason": "No evidence found",
      "evidence": [],
      "evidence_type": "none"
    },
    "Clean Water and Sanitation": {
      "score": 0.0,
      "reason": "No evidence found",
      "evidence": [],
      "evidence_type": "none"
    },
    "Affordable and Clean Energy": {
      "score": 0.0,
      "reason": "No evidence found",
      "evidence": [],
      "evidence_type": "none"
    },
    "Decent Work and Economic Growth": {
      "score": 6.0,
      "reason": "Course prepares students for financial roles, linking to Target 8.3 ('decent job creation').",
      "evidence": [
        "solving financial problems",
        "financial model implementation"
      ],
      "evidence_type": "inferred"
    },
    "Industry, Innovation and Infrastructure": {
      "score": 7.0,
      "reason": "Focus on programming skills for financial applications relates to Target 9.5 ('enhance scientific research').",
      "evidence": [
        "C++ in quantitative finance",
        "financial applications"
      ],
      "evidence_type": "explicit"
    },
    "Reduced Inequalities": {
      "score": 0.0,
      "reason": "No evidence found",
      "evidence": [],
      "evidence_type": "none"
    },
    "Sustainable Cities and Communities": {
      "score": 0.0,
      "reason": "No evidence found",
      "evidence": [],
      "evidence_type": "none"
    },
    "Responsible Consumption and Production": {
      "score": 0.0,
      "reason": "No evidence found",
      "evidence": [],
      "evidence_type": "none"
    },
    "Climate Action": {
      "score": 0.0,
      "reason": "No evidence found",
      "evidence": [],
      "evidence_type": "none"
    },
    "Life Below Water": {
      "score": 0.0,
      "reason": "No evidence found",
      "evidence": [],
      "evidence_type": "none"
    },
    "Life on Land": {
      "score": 0.0,
      "reason": "No evidence found",
      "evidence": [],
      "evidence_type": "none"
    },
    "Peace, Justice and Strong Institutions": {
      "score": 0.0,
      "reason": "No evidence found",
      "evidence": [],
      "evidence_type": "none"
    },
    "Partnerships for the Goals": {
      "score": 0.0,
      "reason": "No evidence found",
      "evidence": [],
      "evidence_type": "none"
    }
  },
  "gemini_answer": [
    {
      "No Poverty": {
        "score": 1.0,
        "reason": "The course on \"Financial Computing\" has a minimal inferred link to Target 1.4 (access to financial services), though the content is purely technical, not application-focused.",
        "evidence": [
          "金融計算",
          "Financial Computing"
        ],
        "evidence_type": "inferred"
      },
      "Zero Hunger": {
        "score": 0.0,
        "reason": "No evidence found",
        "evidence": [],
        "evidence_type": "none"
      },
      "Good Health and Well-being": {
        "score": 0.0,
        "reason": "No evidence found",
        "evidence": [],
        "evidence_type": "none"
      },
      "Quality Education": {
        "score": 8.0,
        "reason": "As a university course, it directly provides tertiary education (Target 4.3) and teaches technical skills like \"programming\" and \"model building\" for employment (Target 4.4).",
        "evidence": [
          "提高學生的程式能力和模型建構能力",
          "Financial Computing with Programming Application (I)"
        ],
        "evidence_type": "explicit"
      },
      "Gender Equality": {
        "score": 0.0,
        "reason": "No evidence found",
        "evidence": [],
        "evidence_type": "none"
      },
      "Clean Water and Sanitation": {
        "score": 0.0,
        "reason": "No evidence found",
        "evidence": [],
        "evidence_type": "none"
      },
      "Affordable and Clean Energy": {
        "score": 0.0,
        "reason": "No evidence found",
        "evidence": [],
        "evidence_type": "none"
      },
      "Decent Work and Economic Growth": {
        "score": 8.5,
        "reason": "The course develops advanced skills in \"Financial Computing,\" directly supporting technological upgrading (Target 8.2) and strengthening the capacity of domestic financial institutions (Target 8.10).",
        "evidence": [
          "金融計算",
          "Financial Computing",
          "提高學生的程式能力和模型建構能力"
        ],
        "evidence_type": "explicit"
      },
      "Industry, Innovation and Infrastructure": {
        "score": 9.0,
        "reason": "The course focuses on applying \"computer science\" and C++ to finance, directly enhancing technological capabilities and encouraging innovation within a key industry, aligning with Target 9.5.",
        "evidence": [
          "運用數學、統計、電腦科學等知識",
          "模型建構能力",
          "QuantLib程式庫原始碼的介紹"
        ],
        "evidence_type": "explicit"
      },
      "Reduced Inequalities": {
        "score": 4.5,
        "reason": "Skills in \"Financial Computing\" and building \"financial models\" are foundational for improving the regulation and monitoring of global financial markets, as mentioned in Target 10.5.",
        "evidence": [
          "金融計算",
          "Financial Computing",
          "金融模型的實現與演算法的設計"
        ],
        "evidence_type": "inferred"
      },
      "Sustainable Cities and Communities": {
        "score": 0.0,
        "reason": "No evidence found",
        "evidence": [],
        "evidence_type": "none"
      },
      "Responsible Consumption and Production": {
        "score": 1.5,
        "reason": "The core competency to \"understand... sustainability issues\" provides a minimal, inferred link to Target 12.6, which encourages companies to adopt sustainable practices and reporting.",
        "evidence": [
          "理解與辨別道德、社會責任與永續議題"
        ],
        "evidence_type": "inferred"
      },
      "Climate Action": {
        "score": 0.0,
        "reason": "No evidence found",
        "evidence": [],
        "evidence_type": "none"
      },
      "Life Below Water": {
        "score": 0.0,
        "reason": "No evidence found",
        "evidence": [],
        "evidence_type": "none"
      },
      "Life on Land": {
        "score": 0.0,
        "reason": "No evidence found",
        "evidence": [],
        "evidence_type": "none"
      },
      "Peace, Justice and Strong Institutions": {
        "score": 4.0,
        "reason": "Skills in \"Financial Computing\" are applicable to reducing illicit financial flows (Target 16.4) and developing more transparent financial institutions (Target 16.6), though this is an inferred application.",
        "evidence": [
          "金融計算",
          "Financial Computing",
          "解決金融問題的學科"
        ],
        "evidence_type": "inferred"
      },
      "Partnerships for the Goals": {
        "score": 5.0,
        "reason": "The course builds capacity in \"computer science\" and \"statistics,\" which supports targets on enhancing the use of enabling technology (Target 17.8) and statistical capacity-building (Target 17.19).",
        "evidence": [
          "運用數學、統計、電腦科學等知識",
          "C++是一種高效、靈活、物件導向的程式語言"
        ],
        "evidence_type": "inferred"
      }
    }
  ],
  "gpt_critique": {
    "critique": "Model B's analysis provides more nuanced interpretations of the course content, leading to necessary revisions in my scores.",
    "revisions": {
      "No Poverty": {
        "your_original": 0.0,
        "model_b_score": 1.0,
        "your_revised": 1.0,
        "reason": "Model B's inference on access to financial services aligns with course content."
      },
      "Decent Work and Economic Growth": {
        "your_original": 6.0,
        "model_b_score": 8.5,
        "your_revised": 8.5,
        "reason": "Model B's emphasis on technological upgrading and financial institutions is well-supported."
      },
      "Industry, Innovation and Infrastructure": {
        "your_original": 7.0,
        "model_b_score": 9.0,
        "your_revised": 9.0,
        "reason": "Model B's focus on technological capabilities and innovation is more accurate."
      },
      "Reduced Inequalities": {
        "your_original": 0.0,
        "model_b_score": 4.5,
        "your_revised": 4.5,
        "reason": "Model B's connection to financial market regulation is valid."
      },
      "Peace, Justice and Strong Institutions": {
        "your_original": 0.0,
        "model_b_score": 4.0,
        "your_revised": 4.0,
        "reason": "Model B's inference on financial computing's relevance to transparency is justified."
      },
      "Partnerships for the Goals": {
        "your_original": 0.0,
        "model_b_score": 5.0,
        "your_revised": 5.0,
        "reason": "Model B's link to capacity-building in technology is appropriate."
      }
    }
  },
  "gemini_critique": {
    "critique": "Model A's analysis provided more specific and robust reasoning for several SDGs, particularly regarding the technical and financial applications of the course content.",
    "revisions": {
      "Decent Work and Economic Growth": {
        "your_original": 6.0,
        "model_b_score": 6.0,
        "your_revised": 8.5,
        "reason": "Model A's link to technological upgrading (8.2) and strengthening financial institutions (8.10) is a better fit for the course's advanced technical skills."
      },
      "Industry, Innovation and Infrastructure": {
        "your_original": 7.0,
        "model_b_score": 7.0,
        "your_revised": 9.0,
        "reason": "Model A's reasoning on enhancing technological capabilities and innovation within finance (9.5) is more comprehensive and aligns better with the course's focus."
      },
      "Responsible Consumption and Production": {
        "your_original": 0.0,
        "model_b_score": 0.0,
        "your_revised": 1.5,
        "reason": "Model A correctly identified the core competency on 'sustainability issues,' providing a minimal, inferred link to Target 12.6."
      },
      "Partnerships for the Goals": {
        "your_original": 0.0,
        "model_b_score": 0.0,
        "your_revised": 5.0,
        "reason": "Model A's reasoning on building capacity in computer science and statistics, supporting enabling technology (17.8) and statistical capacity (17.19), is well-justified."
      }
    }
  },
  "gpt_judge_final": {
    "No Poverty": {
      "final_score": 1.0,
      "source": "synthesized",
      "reasoning": "The course's focus on financial computing implies a connection to financial services, aligning with Target 1.4. This score reflects a minimal but valid inference.",
      "model_comparison": {
        "model_a_original": 0.0,
        "model_a_revised": 1.0,
        "model_b_original": 1.0,
        "model_b_revised": 1.0
      }
    },
    "Zero Hunger": {
      "final_score": 0.0,
      "source": "model_a",
      "reasoning": "Both models found no evidence linking the course to hunger-related targets.",
      "model_comparison": {
        "model_a_original": 0.0,
        "model_a_revised": 0.0,
        "model_b_original": 0.0,
        "model_b_revised": 0.0
      }
    },
    "Good Health and Well-being": {
      "final_score": 0.0,
      "source": "model_a",
      "reasoning": "No evidence was found in either model linking the course to health-related targets.",
      "model_comparison": {
        "model_a_original": 0.0,
        "model_a_revised": 0.0,
        "model_b_original": 0.0,
        "model_b_revised": 0.0
      }
    },
    "Quality Education": {
      "final_score": 8.0,
      "source": "synthesized",
      "reasoning": "Both models recognized the course's contribution to education and skills development, particularly in programming and financial modeling.",
      "model_comparison": {
        "model_a_original": 8.0,
        "model_a_revised": 8.0,
        "model_b_original": 8.0,
        "model_b_revised": 8.0
      }
    },
    "Gender Equality": {
      "final_score": 0.0,
      "source": "model_a",
      "reasoning": "Both models found no evidence linking the course to gender equality targets.",
      "model_comparison": {
        "model_a_original": 0.0,
        "model_a_revised": 0.0,
        "model_b_original": 0.0,
        "model_b_revised": 0.0
      }
    },
    "Clean Water and Sanitation": {
      "final_score": 0.0,
      "source": "model_a",
      "reasoning": "No evidence was found in either model linking the course to water and sanitation targets.",
      "model_comparison": {
        "model_a_original": 0.0,
        "model_a_revised": 0.0,
        "model_b_original": 0.0,
        "model_b_revised": 0.0
      }
    },
    "Affordable and Clean Energy": {
      "final_score": 0.0,
      "source": "model_a",
      "reasoning": "Both models found no evidence linking the course to energy-related targets.",
      "model_comparison": {
        "model_a_original": 0.0,
        "model_a_revised": 0.0,
        "model_b_original": 0.0,
        "model_b_revised": 0.0
      }
    },
    "Decent Work and Economic Growth": {
      "final_score": 8.5,
      "source": "synthesized",
      "reasoning": "The course's focus on financial computing and model implementation supports targets related to decent work and economic growth, particularly in technological upgrading.",
      "model_comparison": {
        "model_a_original": 6.0,
        "model_a_revised": 8.5,
        "model_b_original": 8.5,
        "model_b_revised": 8.5
      }
    },
    "Industry, Innovation and Infrastructure": {
      "final_score": 9.0,
      "source": "synthesized",
      "reasoning": "The course's emphasis on programming and financial applications aligns well with targets on innovation and infrastructure development.",
      "model_comparison": {
        "model_a_original": 7.0,
        "model_a_revised": 9.0,
        "model_b_original": 9.0,
        "model_b_revised": 9.0
      }
    },
    "Reduced Inequalities": {
      "final_score": 4.5,
      "source": "synthesized",
      "reasoning": "The course's focus on financial computing provides foundational skills relevant to improving financial market regulation, aligning with inequality reduction targets.",
      "model_comparison": {
        "model_a_original": 0.0,
        "model_a_revised": 4.5,
        "model_b_original": 4.5,
        "model_b_revised": 4.5
      }
    },
    "Sustainable Cities and Communities": {
      "final_score": 0.0,
      "source": "model_a",
      "reasoning": "Both models found no evidence linking the course to sustainable cities and communities targets.",
      "model_comparison": {
        "model_a_original": 0.0,
        "model_a_revised": 0.0,
        "model_b_original": 0.0,
        "model_b_revised": 0.0
      }
    },
    "Responsible Consumption and Production": {
      "final_score": 1.5,
      "source": "synthesized",
      "reasoning": "The course's core competency on sustainability issues provides a minimal link to responsible consumption and production targets.",
      "model_comparison": {
        "model_a_original": 0.0,
        "model_a_revised": 0.0,
        "model_b_original": 1.5,
        "model_b_revised": 1.5
      }
    },
    "Climate Action": {
      "final_score": 0.0,
      "source": "model_a",
      "reasoning": "No evidence was found in either model linking the course to climate action targets.",
      "model_comparison": {
        "model_a_original": 0.0,
        "model_a_revised": 0.0,
        "model_b_original": 0.0,
        "model_b_revised": 0.0
      }
    },
    "Life Below Water": {
      "final_score": 0.0,
      "source": "model_a",
      "reasoning": "Both models found no evidence linking the course to marine life targets.",
      "model_comparison": {
        "model_a_original": 0.0,
        "model_a_revised": 0.0,
        "model_b_original": 0.0,
        "model_b_revised": 0.0
      }
    },
    "Life on Land": {
      "final_score": 0.0,
      "source": "model_a",
      "reasoning": "No evidence was found in either model linking the course to terrestrial life targets.",
      "model_comparison": {
        "model_a_original": 0.0,
        "model_a_revised": 0.0,
        "model_b_original": 0.0,
        "model_b_revised": 0.0
      }
    },
    "Peace, Justice and Strong Institutions": {
      "final_score": 4.0,
      "source": "synthesized",
      "reasoning": "The course's relevance to financial computing supports targets on transparency and reducing illicit financial flows.",
      "model_comparison": {
        "model_a_original": 0.0,
        "model_a_revised": 4.0,
        "model_b_original": 4.0,
        "model_b_revised": 4.0
      }
    },
    "Partnerships for the Goals": {
      "final_score": 5.0,
      "source": "synthesized",
      "reasoning": "The course's focus on technology and statistics supports targets related to capacity-building and enabling technology.",
      "model_comparison": {
        "model_a_original": 0.0,
        "model_a_revised": 5.0,
        "model_b_original": 5.0,
        "model_b_revised": 5.0
      }
    }
  },
  "gemini_judge_final": {
    "No Poverty": {
      "final_score": 1.0,
      "source": "synthesized",
      "reasoning": "The course's focus on financial computing and programming skills could indirectly contribute to developing financial services, aligning minimally with Target 1.4 (access to financial services).",
      "model_comparison": {
        "model_a_original": 0.0,
        "model_a_revised": 1.0,
        "model_b_original": 1.0,
        "model_b_revised": null
      }
    },
    "Zero Hunger": {
      "final_score": 0.0,
      "source": "synthesized",
      "reasoning": "No direct or indirect evidence in the course content relates to ending hunger, food security, or sustainable agriculture.",
      "model_comparison": {
        "model_a_original": 0.0,
        "model_a_revised": null,
        "model_b_original": 0.0,
        "model_b_revised": null
      }
    },
    "Good Health and Well-being": {
      "final_score": 0.0,
      "source": "synthesized",
      "reasoning": "No direct or indirect evidence in the course content relates to health, well-being, disease prevention, or healthcare services.",
      "model_comparison": {
        "model_a_original": 0.0,
        "model_a_revised": null,
        "model_b_original": 0.0,
        "model_b_revised": null
      }
    },
    "Quality Education": {
      "final_score": 8.5,
      "source": "synthesized",
      "reasoning": "As a university course, it directly provides tertiary education (Target 4.3) and explicitly develops technical and problem-solving skills for employment in finance (Target 4.4).",
      "model_comparison": {
        "model_a_original": 8.0,
        "model_a_revised": null,
        "model_b_original": 8.0,
        "model_b_revised": null
      }
    },
    "Gender Equality": {
      "final_score": 0.0,
      "source": "synthesized",
      "reasoning": "No direct or indirect evidence in the course content relates to gender equality or women's empowerment.",
      "model_comparison": {
        "model_a_original": 0.0,
        "model_a_revised": null,
        "model_b_original": 0.0,
        "model_b_revised": null
      }
    },
    "Clean Water and Sanitation": {
      "final_score": 0.0,
      "source": "synthesized",
      "reasoning": "No direct or indirect evidence in the course content relates to water, sanitation, or hygiene.",
      "model_comparison": {
        "model_a_original": 0.0,
        "model_a_revised": null,
        "model_b_original": 0.0,
        "model_b_revised": null
      }
    },
    "Affordable and Clean Energy": {
      "final_score": 0.0,
      "source": "synthesized",
      "reasoning": "No direct or indirect evidence in the course content relates to affordable and clean energy.",
      "model_comparison": {
        "model_a_original": 0.0,
        "model_a_revised": null,
        "model_b_original": 0.0,
        "model_b_revised": null
      }
    },
    "Decent Work and Economic Growth": {
      "final_score": 8.5,
      "source": "synthesized",
      "reasoning": "The course directly develops advanced financial computing skills, supporting technological upgrading (Target 8.2), decent job creation (Target 8.3), and strengthening financial institutions (Target 8.10).",
      "model_comparison": {
        "model_a_original": 6.0,
        "model_a_revised": 8.5,
        "model_b_original": 8.5,
        "model_b_revised": 8.5
      }
    },
    "Industry, Innovation and Infrastructure": {
      "final_score": 9.0,
      "source": "synthesized",
      "reasoning": "The course directly enhances technological capabilities and encourages innovation in the financial industry through the application of computer science and C++ programming (Target 9.5).",
      "model_comparison": {
        "model_a_original": 7.0,
        "model_a_revised": 9.0,
        "model_b_original": 9.0,
        "model_b_revised": 9.0
      }
    },
    "Reduced Inequalities": {
      "final_score": 4.5,
      "source": "synthesized",
      "reasoning": "The advanced financial computing and model-building skills taught are foundational for improving the regulation and monitoring of financial markets (Target 10.5), indirectly contributing to reduced inequalities.",
      "model_comparison": {
        "model_a_original": 0.0,
        "model_a_revised": 4.5,
        "model_b_original": 4.5,
        "model_b_revised": null
      }
    },
    "Sustainable Cities and Communities": {
      "final_score": 0.0,
      "source": "synthesized",
      "reasoning": "No direct or indirect evidence in the course content relates to sustainable cities and communities.",
      "model_comparison": {
        "model_a_original": 0.0,
        "model_a_revised": null,
        "model_b_original": 0.0,
        "model_b_revised": null
      }
    },
    "Responsible Consumption and Production": {
      "final_score": 1.5,
      "source": "model_b",
      "reasoning": "Core Competency D, 'understand and identify ethics, social responsibility, and sustainability issues,' provides a minimal, inferred link to encouraging sustainable practices (Target 12.6).",
      "model_comparison": {
        "model_a_original": 0.0,
        "model_a_revised": null,
        "model_b_original": 1.5,
        "model_b_revised": 1.5
      }
    },
    "Climate Action": {
      "final_score": 0.0,
      "source": "synthesized",
      "reasoning": "No direct or indirect evidence in the course content relates to climate action.",
      "model_comparison": {
        "model_a_original": 0.0,
        "model_a_revised": null,
        "model_b_original": 0.0,
        "model_b_revised": null
      }
    },
    "Life Below Water": {
      "final_score": 0.0,
      "source": "synthesized",
      "reasoning": "No direct or indirect evidence in the course content relates to marine life or ocean conservation.",
      "model_comparison": {
        "model_a_original": 0.0,
        "model_a_revised": null,
        "model_b_original": 0.0,
        "model_b_revised": null
      }
    },
    "Life on Land": {
      "final_score": 0.0,
      "source": "synthesized",
      "reasoning": "No direct or indirect evidence in the course content relates to terrestrial ecosystems or biodiversity.",
      "model_comparison": {
        "model_a_original": 0.0,
        "model_a_revised": null,
        "model_b_original": 0.0,
        "model_b_revised": null
      }
    },
    "Peace, Justice and Strong Institutions": {
      "final_score": 4.0,
      "source": "synthesized",
      "reasoning": "Financial computing skills can be applied to develop systems for detecting illicit financial flows (Target 16.4) and enhancing transparency in financial institutions (Target 16.6).",
      "model_comparison": {
        "model_a_original": 0.0,
        "model_a_revised": 4.0,
        "model_b_original": 4.0,
        "model_b_revised": null
      }
    },
    "Partnerships for the Goals": {
      "final_score": 5.0,
      "source": "synthesized",
      "reasoning": "The course builds capacity in computer science, mathematics, and statistics, directly supporting enabling technology (Target 17.8) and statistical capacity-building (Target 17.19) for SDG implementation.",
      "model_comparison": {
        "model_a_original": 0.0,
        "model_a_revised": 5.0,
        "model_b_original": 5.0,
        "model_b_revised": 5.0
      }
    }
  }
}